nldi_el_serv/PathGen.py
nldi_el_serv/XSGen.py
nldi_el_serv/__init__.py
nldi_el_serv/__openChannel.py
nldi_el_serv/centerline.py
nldi_el_serv/cli.py
nldi_el_serv/dem_query.py
nldi_el_serv/nldi_el_serv.py
nldi_el_serv/tspline.py
nldi_el_serv-0.1.5.dist-info/AUTHORS.rst
nldi_el_serv-0.1.5.dist-info/LICENSE
nldi_el_serv-0.1.5.dist-info/METADATA
nldi_el_serv-0.1.5.dist-info/WHEEL
nldi_el_serv-0.1.5.dist-info/entry_points.txt
nldi_el_serv-0.1.5.dist-info/top_level.txt
nldi_el_serv-0.1.5.dist-info/RECORD
