Metadata-Version: 2.1
Name: nldi-el-serv
Version: 0.1.5
Summary: NLDI Elevation Services
Home-page: https://github.com/ACWI-SSWD/nldi_el_serv
Author: Richard McDonald
Author-email: rmcd@usgs.gov
License: CC0 1.0 Universal public domain dedication
Keywords: nldi_el_serv
Platform: UNKNOWN
Classifier: Development Status :: 2 - Pre-Alpha
Classifier: Intended Audience :: Developers
Classifier: License :: CC0 1.0 Universal (CC0 1.0) Public Domain Dedication
Classifier: Natural Language :: English
Classifier: Programming Language :: Python :: 3.8
Requires-Python: >=3.8
Requires-Dist: Click (>=7.0)
Requires-Dist: pygeohydro (==0.10.2)
Requires-Dist: py3dep (==0.10.1)
Requires-Dist: pygeoogc (==0.10.1)
Requires-Dist: pygeoutils (==0.10.1)
Requires-Dist: pynhd (==0.10.1)
Requires-Dist: dataretrieval (==0.7)
Requires-Dist: folium (==0.0.0)
Requires-Dist: lxml (==4.6.3)
Requires-Dist: matplotlib (==3.4.1)
Requires-Dist: xarray (==0.17.0)
Requires-Dist: scipy (==1.6.2)
Requires-Dist: dask (==2021.4.0)
Requires-Dist: netcdf4 (==1.5.6)
Requires-Dist: bottleneck (==1.3.2)
Requires-Dist: jupyterlab (==3.0.14)
Requires-Dist: geopandas (==0.9.0)
Requires-Dist: descartes (==1.1.0)
Requires-Dist: numba (==0.53.1)
